boundml/__init__.py
boundml/components/__init__.py
boundml/components/branching_components.py
boundml/components/components.py
boundml/components/conditional_component.py
boundml/components/ecole_component.py
boundml/components/gnn_component.py
boundml/core/__init__.py
boundml/core/branchrule.py
boundml/core/utils.py
boundml/evaluation/__init__.py
boundml/evaluation/evaluation_tools.py
boundml/evaluation/solver_evaluation_results.py
boundml/instances/__init__.py
boundml/instances/ecole_instances.py
boundml/instances/folder_instances.py
boundml/instances/instances.py
boundml/instances/miplib.py
boundml/ml/__init__.py
boundml/ml/branching_dataset_generator.py
boundml/ml/model.py
boundml/solvers/__init__.py
boundml/solvers/modular_solver.py
boundml/solvers/solvers.py
boundml-1.3.0.dist-info/licenses/LICENSE
boundml-1.3.0.dist-info/METADATA
boundml-1.3.0.dist-info/WHEEL
boundml-1.3.0.dist-info/top_level.txt
boundml-1.3.0.dist-info/RECORD
