Metadata-Version: 2.4
Name: boundml
Version: 1.3.0
Summary: BoundML is a toolbox to evaluate and compare branch and bound solvers. It allows to easily develop and compare new machine learning based (or not) branching strategies for the Branch and Bound.
Author-email: Simon Renard <simon.renard@ulb.be>
License: MIT License
Project-URL: Homepage, https://github.com/sirenard/BoundML
Classifier: Programming Language :: Python :: 3
Classifier: License :: OSI Approved :: MIT License
Classifier: Operating System :: OS Independent
Requires-Python: >=3.7
License-File: LICENSE
Requires-Dist: appdirs
Requires-Dist: ecole-fork
Requires-Dist: pyscipopt
Requires-Dist: pathos
Requires-Dist: dill
Requires-Dist: torch
Requires-Dist: torchvision
Requires-Dist: torchaudio
Requires-Dist: torch_geometric
Requires-Dist: matplotlib
Requires-Dist: pandas
Requires-Dist: tabulate
Dynamic: license-file
